<?xml version="1.0"?>
<ArrayOfDrone xmlns:xsi="http://www.w3.org/2001/XMLSchema-instance" xmlns:xsd="http://www.w3.org/2001/XMLSchema">
  <Drone>
    <Id>44448</Id>
    <Model>lion</Model>
    <MaxWeight>Light</MaxWeight>
  </Drone>
  <Drone>
    <Id>44590</Id>
    <Model>Sentinel</Model>
    <MaxWeight>Medium</MaxWeight>
  </Drone>
  <Drone>
    <Id>44068</Id>
    <Model>lion</Model>
    <MaxWeight>Heavy</MaxWeight>
  </Drone>
  <Drone>
    <Id>68686</Id>
    <Model>Sentinel</Model>
    <MaxWeight>Medium</MaxWeight>
  </Drone>
  <Drone>
    <Id>5570</Id>
    <Model>flybird</Model>
    <MaxWeight>Medium</MaxWeight>
  </Drone>
  <Drone>
    <Id>38023</Id>
    <Model>worm</Model>
    <MaxWeight>Medium</MaxWeight>
  </Drone>
  <Drone>
    <Id>35586</Id>
    <Model>mavic</Model>
    <MaxWeight>Heavy</MaxWeight>
  </Drone>
  <Drone>
    <Id>61270</Id>
    <Model>beck</Model>
    <MaxWeight>Heavy</MaxWeight>
  </Drone>
  <Drone>
    <Id>76052</Id>
    <Model>Hawk</Model>
    <MaxWeight>Heavy</MaxWeight>
  </Drone>
  <Drone>
    <Id>77753</Id>
    <Model>Sentinel</Model>
    <MaxWeight>Heavy</MaxWeight>
  </Drone>
</ArrayOfDrone>