<?xml version="1.0" encoding="utf-8"?>
<ArrayOfParcel xmlns:xsi="http://www.w3.org/2001/XMLSchema-instance" xmlns:xsd="http://www.w3.org/2001/XMLSchema">
  <Parcel>
    <Id>1</Id>
    <SenderId>739577997</SenderId>
    <TargetId>187197868</TargetId>
    <DroneId>0</DroneId>
    <Weight>Light</Weight>
    <Priority>Express</Priority>
    <Creating>2022-01-06T15:10:24.4416415+02:00</Creating>
    <Affiliation xsi:nil="true" />
    <PickedUp xsi:nil="true" />
    <Delivered xsi:nil="true" />
  </Parcel>
  <Parcel>
    <Id>2</Id>
    <SenderId>665034997</SenderId>
    <TargetId>665034997</TargetId>
    <DroneId>0</DroneId>
    <Weight>Medium</Weight>
    <Priority>Express</Priority>
    <Creating>2022-01-06T15:10:24.4468675+02:00</Creating>
    <Affiliation xsi:nil="true" />
    <PickedUp xsi:nil="true" />
    <Delivered xsi:nil="true" />
  </Parcel>
  <Parcel>
    <Id>3</Id>
    <SenderId>745436949</SenderId>
    <TargetId>180401952</TargetId>
    <DroneId>0</DroneId>
    <Weight>Medium</Weight>
    <Priority>Regular</Priority>
    <Creating>2022-01-06T15:10:24.4468738+02:00</Creating>
    <Affiliation xsi:nil="true" />
    <PickedUp xsi:nil="true" />
    <Delivered xsi:nil="true" />
  </Parcel>
  <Parcel>
    <Id>4</Id>
    <SenderId>739577997</SenderId>
    <TargetId>361189343</TargetId>
    <DroneId>68686</DroneId>
    <Weight>Medium</Weight>
    <Priority>Express</Priority>
    <Creating>2022-01-06T14:10:24.4470106+02:00</Creating>
    <Affiliation>2022-01-06T14:40:24.4470147+02:00</Affiliation>
    <PickedUp xsi:nil="true" />
    <Delivered xsi:nil="true" />
  </Parcel>
  <Parcel>
    <Id>5</Id>
    <SenderId>516772050</SenderId>
    <TargetId>516772050</TargetId>
    <DroneId>5570</DroneId>
    <Weight>Medium</Weight>
    <Priority>Express</Priority>
    <Creating>2022-01-06T14:10:24.4470163+02:00</Creating>
    <Affiliation>2022-01-06T14:40:24.4470167+02:00</Affiliation>
    <PickedUp xsi:nil="true" />
    <Delivered xsi:nil="true" />
  </Parcel>
  <Parcel>
    <Id>6</Id>
    <SenderId>516772050</SenderId>
    <TargetId>739577997</TargetId>
    <DroneId>38023</DroneId>
    <Weight>Medium</Weight>
    <Priority>Express</Priority>
    <Creating>2022-01-06T14:10:24.4470182+02:00</Creating>
    <Affiliation>2022-01-06T14:40:24.4470186+02:00</Affiliation>
    <PickedUp xsi:nil="true" />
    <Delivered xsi:nil="true" />
  </Parcel>
  <Parcel>
    <Id>7</Id>
    <SenderId>745436949</SenderId>
    <TargetId>180401952</TargetId>
    <DroneId>35586</DroneId>
    <Weight>Heavy</Weight>
    <Priority>Regular</Priority>
    <Creating>2022-01-06T13:10:24.4470195+02:00</Creating>
    <Affiliation>2022-01-06T13:40:24.4470198+02:00</Affiliation>
    <PickedUp>2022-01-06T14:10:24.4470202+02:00</PickedUp>
    <Delivered xsi:nil="true" />
  </Parcel>
  <Parcel>
    <Id>8</Id>
    <SenderId>745436949</SenderId>
    <TargetId>409281334</TargetId>
    <DroneId>61270</DroneId>
    <Weight>Heavy</Weight>
    <Priority>Regular</Priority>
    <Creating>2022-01-06T13:10:24.4470209+02:00</Creating>
    <Affiliation>2022-01-06T13:40:24.4470213+02:00</Affiliation>
    <PickedUp>2022-01-06T14:10:24.4470217+02:00</PickedUp>
    <Delivered xsi:nil="true" />
  </Parcel>
  <Parcel>
    <Id>9</Id>
    <SenderId>308636059</SenderId>
    <TargetId>409281334</TargetId>
    <DroneId>0</DroneId>
    <Weight>Heavy</Weight>
    <Priority>Regular</Priority>
    <Creating>2022-01-06T12:10:24.4470226+02:00</Creating>
    <Affiliation>2022-01-06T13:10:24.4470238+02:00</Affiliation>
    <PickedUp>2022-01-06T13:40:24.4470234+02:00</PickedUp>
    <Delivered>2022-01-06T14:40:24.447023+02:00</Delivered>
  </Parcel>
  <Parcel>
    <Id>10</Id>
    <SenderId>516772050</SenderId>
    <TargetId>745436949</TargetId>
    <DroneId>0</DroneId>
    <Weight>Heavy</Weight>
    <Priority>Regular</Priority>
    <Creating>2022-01-06T12:10:24.4470341+02:00</Creating>
    <Affiliation>2022-01-06T13:10:24.4470353+02:00</Affiliation>
    <PickedUp>2022-01-06T13:40:24.4470349+02:00</PickedUp>
    <Delivered>2022-01-06T14:40:24.4470345+02:00</Delivered>
  </Parcel>
  <Station>
    <Id>11</Id>
    <SenderId>745436949</SenderId>
    <TargetId>739577997</TargetId>
    <DroneId>0</DroneId>
    <Weight>Light</Weight>
    <Priority>Regular</Priority>
    <Creating>2022-01-06T15:12:02.5423849+02:00</Creating>
    <Affiliation />
    <PickedUp />
    <Delivered />
  </Station>
  <Station>
    <Id>12</Id>
    <SenderId>745436949</SenderId>
    <TargetId>739577997</TargetId>
    <DroneId>0</DroneId>
    <Weight>Light</Weight>
    <Priority>Regular</Priority>
    <Creating>2022-01-06T15:14:33.0349518+02:00</Creating>
    <Affiliation />
    <PickedUp />
    <Delivered />
  </Station>
  <Station>
    <Id>13</Id>
    <SenderId>745436949</SenderId>
    <TargetId>739577997</TargetId>
    <DroneId>0</DroneId>
    <Weight>Light</Weight>
    <Priority>Regular</Priority>
    <Creating>2022-01-06T15:16:12.3257439+02:00</Creating>
    <Affiliation />
    <PickedUp />
    <Delivered />
  </Station>
</ArrayOfParcel>